{"cameraMode":{"drawMode":0,"name":"Shaded","section":"Shading Mode"},"sceneLighting":true,"audioPlay":false,"sceneViewState":{"m_AlwaysRefresh":false,"showFog":true,"showSkybox":true,"showFlares":true,"showImageEffects":true,"showParticleSystems":true,"showVisualEffectGraphs":true,"m_FxEnabled":true},"in2DMode":false,"pivot":{"x":13.780407905578614,"y":3.37508487701416,"z":5.37489128112793},"rotation":{"x":-0.28879979252815249,"y":0.33587023615837099,"z":-0.10900186002254486,"w":-0.8898935914039612},"size":12.12435531616211,"orthographic":false}